[
  {
    "id": 1,
    "name": "Physics",
    "image": "https://g.christianbook.com/dg/product/web/f400/169958.jpg"
  },
  {


    "id": 2,

    "name": "Chemisty",
    "image": "https://chemistryhall.com/wp-content/uploads/2019/08/chemgen.jpg"
  },
  {
    "id": 3,
    "name": "Biology",
    "image": "https://qph.cf2.quoracdn.net/main-qimg-3dbba18fc6c30318535ec4e819718d1e-lq"
  },
  {
    "id": 4,
    "name": "Mathematics",
    "image": "https://comptes-books.com/wp-content/uploads/2021/03/TOP-Math-Textbook-6B.jpg"
  },
  {
    "id": 5,
    "name": "Computer Science",
    "image": "https://www.cambridgeinternational.org/Images/9781398318281.jpg"
  },
  {
    "id": 1,
    "name": "Physics",
    "image": "https://g.christianbook.com/dg/product/web/f400/169958.jpg"
  },
  {


    "id": 2,

    "name": "Chemisty",
    "image": "https://chemistryhall.com/wp-content/uploads/2019/08/chemgen.jpg"
  },
  {
    "id": 3,
    "name": "Biology",
    "image": "https://qph.cf2.quoracdn.net/main-qimg-3dbba18fc6c30318535ec4e819718d1e-lq"
  },
  {
    "id": 4,
    "name": "Mathematics",
    "image": "https://comptes-books.com/wp-content/uploads/2021/03/TOP-Math-Textbook-6B.jpg"
  },
  {
    "id": 5,
    "name": "Computer Science",
    "image": "https://www.cambridgeinternational.org/Images/9781398318281.jpg"
  }
]
